mpl_pymanage/__init__.py
mpl_pymanage/__main__.py
mpl_pymanage/add.py
mpl_pymanage/create.py
mpl_pymanage/deploy.py
mpl_pymanage/mpl_pymanage.py
mpl_pymanage/run.py
mpl_pymanage/utils.py
mpl_pymanage/validators.py
mpl_pymanage/templates/.gitignore
mpl_pymanage/templates/README.md
mpl_pymanage/templates/check.yml
mpl_pymanage/templates/mpl_pymanage.txt
mpl_pymanage/templates/setup.py
mpl_pymanage/templates/source.py
mpl_pymanage/templates/test.py
mpl_pymanage/templates/licenses/Apache
mpl_pymanage/templates/licenses/GPLv3
mpl_pymanage/templates/licenses/MIT
mpl_pymanage-0.1.1.dist-info/LICENSE
mpl_pymanage-0.1.1.dist-info/METADATA
mpl_pymanage-0.1.1.dist-info/WHEEL
mpl_pymanage-0.1.1.dist-info/entry_points.txt
mpl_pymanage-0.1.1.dist-info/top_level.txt
mpl_pymanage-0.1.1.dist-info/RECORD
