Metadata-Version: 2.1
Name: mpl-pymanage
Version: 0.1.1
Summary: A CLI for managing Python projects.
Home-page: https://github.com/MPL-IT/mpl_pymanage
Author: Matthias Baer
Author-email: matthias.baer@mpl.mpg.de
License: GPL v3
Keywords: CLI,cli,Python project management
Platform: ALL
Classifier: Operating System :: OS Independent
Classifier: Programming Language :: Python :: 3
Classifier: Intended Audience :: Developers
Classifier: Environment :: Console
Requires-Python: >=3.6
License-File: LICENSE
Requires-Dist: Click
Requires-Dist: sphinx
